Metadata-Version: 1.0
Name: bgg-distributions
Version: 0.1
Summary: Binomial, Gaussian and General distributions
Home-page: UNKNOWN
Author: UNKNOWN
Author-email: UNKNOWN
License: UNKNOWN
Platform: UNKNOWN
